{
  "/_not-found/page": "app/_not-found/page.js",
  "/api/admin/create/route": "app/api/admin/create/route.js",
  "/api/admin/logout/route": "app/api/admin/logout/route.js",
  "/api/pin/set/route": "app/api/pin/set/route.js",
  "/api/pin/verify/route": "app/api/pin/verify/route.js",
  "/auth/admin/login/page": "app/auth/admin/login/page.js",
  "/auth/complete/page": "app/auth/complete/page.js",
  "/auth/database/page": "app/auth/database/page.js",
  "/auth/debug/page": "app/auth/debug/page.js",
  "/auth/login/page": "app/auth/login/page.js",
  "/auth/pin-client/page": "app/auth/pin-client/page.js",
  "/auth/pin-setup-client/page": "app/auth/pin-setup-client/page.js",
  "/auth/pin-setup/page": "app/auth/pin-setup/page.js",
  "/auth/pin/page": "app/auth/pin/page.js",
  "/auth/register/page": "app/auth/register/page.js",
  "/auth/sign-in/page": "app/auth/sign-in/page.js",
  "/auth/sign-up/page": "app/auth/sign-up/page.js",
  "/auth/test/page": "app/auth/test/page.js",
  "/page": "app/page.js",
  "/(main)/cards/page": "app/(main)/cards/page.js",
  "/(main)/deposit/page": "app/(main)/deposit/page.js",
  "/(main)/payout-methods/page": "app/(main)/payout-methods/page.js",
  "/(main)/stats/page": "app/(main)/stats/page.js",
  "/(main)/profile/page": "app/(main)/profile/page.js",
  "/(main)/transactions/page": "app/(main)/transactions/page.js",
  "/(main)/withdraw/page": "app/(main)/withdraw/page.js",
  "/admin/accounts/page": "app/admin/accounts/page.js",
  "/admin/dashboard/page": "app/admin/dashboard/page.js",
  "/admin/login/page": "app/admin/login/page.js",
  "/admin/page": "app/admin/page.js",
  "/admin/settings/page": "app/admin/settings/page.js",
  "/admin/transactions/page": "app/admin/transactions/page.js",
  "/admin/users/page": "app/admin/users/page.js",
  "/(main)/dashboard/page": "app/(main)/dashboard/page.js"
}